streambotapi/__init__.py
streambotapi-1.2.4.dist-info/METADATA
streambotapi-1.2.4.dist-info/WHEEL
streambotapi-1.2.4.dist-info/RECORD
