Metadata-Version: 2.1
Name: streambotapi
Version: 1.2.4
Summary: A WebSocket development server for interaction with StreamBot package
Home-page: https://github.com/dr00-eth/StreamBotAPI
License: MIT
Keywords: chatgpt,stream,openai,websocket,flask,socketio,gpt,python
Author: dr00
Author-email: andrewmeyer23@gmail.com
Requires-Python: >=3.10,<4.0
Classifier: License :: OSI Approved :: MIT License
Classifier: Programming Language :: Python :: 3
Classifier: Programming Language :: Python :: 3.10
Classifier: Programming Language :: Python :: 3.11
Requires-Dist: eventlet (>=0.33.3,<0.34.0)
Requires-Dist: flask (>=2.2.3,<3.0.0)
Requires-Dist: flask-cors (>=3.0.10,<4.0.0)
Requires-Dist: flask-socketio (>=5.3.2,<6.0.0)
Requires-Dist: streambot (>=1.1.9,<2.0.0)
Requires-Dist: tiktoken (>=0.3.2,<0.4.0)
Project-URL: Repository, https://github.com/dr00-eth/StreamBotAPI
